swimnetworks/__init__.py
swimnetworks/base.py
swimnetworks/deeponet.py
swimnetworks/dense.py
swimnetworks/fourier.py
swimnetworks/linear.py
swimnetworks-0.0.2.dist-info/licenses/CONTRIBUTORS
swimnetworks-0.0.2.dist-info/licenses/LICENSE
swimnetworks-0.0.2.dist-info/METADATA
swimnetworks-0.0.2.dist-info/WHEEL
swimnetworks-0.0.2.dist-info/top_level.txt
swimnetworks-0.0.2.dist-info/RECORD
