Metadata-Version: 2.4
Name: swimnetworks
Version: 0.0.2
Summary: SWIM training of neural networks.
Author: Erik Bolager, Iryna Burak, Chinmay Datar, Qing Sun
Author-email: Felix Dietrich <felix.dietrich@tum.de>
License-Expression: MIT
Project-URL: Homepage, https://gitlab.com/fd-research/swimnetworks
Project-URL: Bug Tracker, https://gitlab.com/fd-research/swimnetworks/-/issues
Classifier: Programming Language :: Python :: 3
Classifier: Programming Language :: Python :: 3 :: Only
Classifier: Operating System :: OS Independent
Classifier: Intended Audience :: Science/Research
Classifier: Topic :: Scientific/Engineering :: Artificial Intelligence
Requires-Python: >=3.10
License-File: LICENSE
License-File: CONTRIBUTORS
Requires-Dist: numpy>=1.23.5
Requires-Dist: scikit-learn>=1.2.2
Dynamic: license-file
